CHANGES.rst
CREDITS.rst
LICENSE.txt
MANIFEST.in
README.rst
setup.py
collective/__init__.py
collective.elephantvocabulary.egg-info/PKG-INFO
collective.elephantvocabulary.egg-info/SOURCES.txt
collective.elephantvocabulary.egg-info/dependency_links.txt
collective.elephantvocabulary.egg-info/entry_points.txt
collective.elephantvocabulary.egg-info/namespace_packages.txt
collective.elephantvocabulary.egg-info/not-zip-safe
collective.elephantvocabulary.egg-info/requires.txt
collective.elephantvocabulary.egg-info/top_level.txt
collective/elephantvocabulary/__init__.py
collective/elephantvocabulary/base.py
collective/elephantvocabulary/hidden.py
collective/elephantvocabulary/interfaces.py
collective/elephantvocabulary/test_terms_from_registry.rst
collective/elephantvocabulary/testing.py
collective/elephantvocabulary/tests.py
collective/elephantvocabulary/tests.rst
collective/elephantvocabulary/visible.py
collective/elephantvocabulary/vocabulary.py