Metadata-Version: 1.1
Name: collective.elephantvocabulary
Version: 0.2.4
Summary: type of zope vocabularies that dont "forget", like                    elephants
Home-page: http://github.com/collective/collective.elephantvocabulary
Author: Rok Garbas
Author-email: rok@garbas.si
License: GPL
Keywords: zope plone vocabulary
Platform: UNKNOWN
Classifier: Programming Language :: Python
Classifier: Programming Language :: Zope
Classifier: License :: OSI Approved :: GNU General Public License (GPL)
